MANIFEST.in
README.rst
setup.cfg
setup.py
resources/init/static/css/main.css
resources/init/static/images/splash-background.png
resources/init/static/lib/pysite.js
resources/init/templates/main.jinja
script/templates/pysite
script/templates/pysite.bat
scripts/pysite-2.7
src/pysite/__init__.py
src/pysite/compat.py
src/pysite.egg-info/PKG-INFO
src/pysite.egg-info/SOURCES.txt
src/pysite.egg-info/dependency_links.txt
src/pysite.egg-info/not-zip-safe
src/pysite.egg-info/requires.txt
src/pysite.egg-info/top_level.txt
src/pysite/conf/__init__.py
src/pysite/exceptions/__init__.py
src/pysite/exceptions/conf.py
src/pysite/localization/__init__.py
src/pysite/subhandlers/__init__.py
src/pysite/subhandlers/downloadhandler.py
src/pysite/tools/__init__.py
src/pysite/tools/httptools.py
src/pysite/tools/log.py
src/pysite/tools/lrelease.py
src/pysite/tools/lupdate.py
src/pysite/wsgi/__init__.py
src/pysite/wsgi/httpheader.py