Metadata-Version: 1.1
Name: pysite
Version: 0.3.2
Summary: Create simple yet powerful WSGI based sites, utilizing Jinja2 and Qt's TS-file format for localization
Home-page: UNKNOWN
Author: Jakob Simon-Gaarde
Author-email: jakob@simon-gaarde.dk
License: LGPL3
Keywords: wsgi,website,www,website,framework
Platform: UNKNOWN
Classifier: Programming Language :: Python
Classifier: Programming Language :: Python :: 2
Classifier: Programming Language :: Python :: 3
Classifier: Operating System :: OS Independent
Classifier: Natural Language :: English
Classifier: Intended Audience :: Developers
Classifier: Topic :: Internet :: WWW/HTTP :: WSGI :: Application
Requires: jinja2
Requires: slimit
Provides: pysite
